{
	"mindshield": {
		"name": "Mindshield",
		"type": "combat",
		"targetType": "CREATURE",
		"school": {
			"air": true,
			"earth": false,
			"fire": false,
			"water": false
		},
		"level": 3,
		"power": 1,
		"defaultGainChance": 0,
		"flags": {
			"positive": true
			//"special" : true add comma
		},
		"counters" : {
			"spell.blind" : true,
			"spell.berserk" : true,
			"spell.frenzy" : true,
			"spell.forgetfulness" : true,
			"spell.hypnotize" : true,
			"spell.sorrow" : true
		},
		"levels": {
			"base": {
				"power": 1,
				"cost": 20,
				"range": "0",
				"targetModifier": {
					"smart": true
				},
				"battleEffects": {
					"effect1": {
						"type": "core:timed",
						"bonus": {
							"shield" : {
								"type": "MIND_IMMUNITY",
								"valueType": "BASE_NUMBER",
								"duration": "N_TURNS",
								"turns": 1
							},
							"morale" : {
								"type": "MORALE",
								"val" : 0,
								"valueType": "INDEPENDENT_MAX",
								"duration": "N_TURNS",
								"turns": 1
							}
						}
					}
				}
			},
			"none": {
				"description": "{Base Mindshield}\r\n\r\nThe spell grants immunity to mind-affecting spells to a selected group. Additionally dispels negative statuses of mind and sets mimimum morale to 0.\r\n\r\nEffects last for 1 turn."
			},
			"basic": {
				"description": "{Basic Mindshield}\r\n\r\nThe spell grants immunity to mind-affecting spells to a selected group. Additionally dispels negative statuses of mind and sets mimimum morale to 0. Effects last for 2 turns.",
				"cost": 15,
				"battleEffects": {
					"effect1": {
						"bonus": {
							"shield" : {
								"turns" : 2
							},
							"morale" : {
								"turns" : 2
							}
						}
					}
				}
			},
			"advanced": {
				"description": "{Advanced Mindshield}\r\n\r\nThe spell grants immunity to mind-affecting spells to a selected group. Additionally dispels negative statuses of mind and sets mimimum morale to 0. Effects last for 5 turns.",
				"cost": 10,
				"battleEffects": {
					"effect1": {
						"bonus": {
							"shield" : {
								"turns" : 5
							},
							"morale" : {
								"turns" : 5
							}
						}
					}
				}
			},
			"expert": {
				"description": "{Expert Mindshield}\r\n\r\nThe spell grants immunity to mind-affecting spells to hero's army. Additionally dispels negative statuses of mind and sets mimimum morale to 0. Effects last for 10 turns.",
				"cost": 10,
				"range": "X",
				"battleEffects": {
					"effect1": {
						"bonus": {
							"shield" : {
								"turns" : 10
							},
							"morale" : {
								"turns" : 10
							}
						}
					}
				}
			}
		},
		"animation": {
			"affect": [
				"C02SPE0"
			]
		},
		"graphics": {
			"iconScenarioBonus": "mindshield/spellScenario",
			"iconEffect": "mindshield/spellEffect",
			"iconBook": "mindshield/spellBook",
			"iconScroll": "mindshield/spellScroll"
		},
		"sounds": {
			"cast": "PROTECTA"
		}
	}
}
